pyrustats/__init__.py
pyrustats/distributions/__init__.py
pyrustats/distributions/Binomialdistribution.py
pyrustats/distributions/Gaussiandistribution.py
pyrustats/distributions/Generaldistribution.py
pyrustats-0.2.1.2.dist-info/LICENSE
pyrustats-0.2.1.2.dist-info/METADATA
pyrustats-0.2.1.2.dist-info/WHEEL
pyrustats-0.2.1.2.dist-info/RECORD
