Metadata-Version: 2.1
Name: pyrustats
Version: 0.2.1.2
Summary: Basic data structures for statistics
License: MIT
Keywords: statistics,distributions
Author: Ruukha
Author-email: ruukha3@gmail.com
Requires-Python: >=3.11.9
Classifier: License :: OSI Approved :: MIT License
Classifier: Programming Language :: Python :: 3
Classifier: Programming Language :: Python :: 3.12
Requires-Dist: matplotlib (>=3.9.1)
